setup.py
helloworldsaksham/__init__.py
helloworldsaksham/helloworldsaksham.py
helloworldsaksham.egg-info/PKG-INFO
helloworldsaksham.egg-info/SOURCES.txt
helloworldsaksham.egg-info/dependency_links.txt
helloworldsaksham.egg-info/not-zip-safe
helloworldsaksham.egg-info/top_level.txt