Metadata-Version: 1.0
Name: helloworldsaksham
Version: 0.1
Summary: Say Hello Saksham to the world
Home-page: UNKNOWN
Author: Saksham Phul
Author-email: sakshamphul2@gmail.com
License: UNKNOWN
Platform: UNKNOWN
